MIPMLP/CNN2convlayer.py
MIPMLP/ForExample.py
MIPMLP/PLSuperModel.py
MIPMLP/__init__.py
MIPMLP/calculate_hill_index.py
MIPMLP/create_otu_and_mapping_files.py
MIPMLP/distance_learning_func.py
MIPMLP/example_code_run_imic.py
MIPMLP/for_pypi_micro2_matrix.py
MIPMLP/general.py
MIPMLP/plot_boxplot.py
MIPMLP/plot_relative_frequency.py
MIPMLP/preprocess_grid.py
MIPMLP/service.py
MIPMLP/subpca_by_taxonomy.py
MIPMLP/textreeCreate.py
mipmlp-1.2.19.dist-info/METADATA
mipmlp-1.2.19.dist-info/WHEEL
mipmlp-1.2.19.dist-info/top_level.txt
mipmlp-1.2.19.dist-info/RECORD
