Metadata-Version: 2.4
Name: MIPMLP
Version: 1.2.19
Author-email: Oshrit Shtossel <oshritvig@gmail.com>, Yuli Tshuva <yuli.tshuva@gmail.com>
Classifier: License :: OSI Approved :: MIT License
Classifier: Programming Language :: Python
Classifier: Programming Language :: Python :: 3
Requires-Python: >=3.7
Requires-Dist: numpy>=1.24.3
Requires-Dist: pandas>=1.3.4
Requires-Dist: scipy>=1.5.0
Requires-Dist: networkx>=2.5.1
Requires-Dist: matplotlib
Requires-Dist: scikit-learn
Requires-Dist: plotly
Requires-Dist: tqdm
Requires-Dist: igraph
Requires-Dist: pytorch-lightning>=2.1.0
Requires-Dist: torch>=2.1.0
